peerdomclient/__init__.py
peerdomclient/peerdomclient.py
peerdomclient-0.1.1.dist-info/LICENSE
peerdomclient-0.1.1.dist-info/METADATA
peerdomclient-0.1.1.dist-info/WHEEL
peerdomclient-0.1.1.dist-info/RECORD
