Metadata-Version: 2.1
Name: peerdomclient
Version: 0.1.1
Summary: Peerdom's Python api wrapper developed by Peerdom
Home-page: https://github.com/peerdom/peerdom-client-python/
Author: Peerdom
Author-email: hello@peerdom.org
Requires-Python: >=3.8,<4.0
Classifier: Programming Language :: Python :: 3
Classifier: Programming Language :: Python :: 3.8
Classifier: Programming Language :: Python :: 3.9
Classifier: Programming Language :: Python :: 3.10
Classifier: Programming Language :: Python :: 3.11
Classifier: Programming Language :: Python :: 3.12
Requires-Dist: Requests (==2.31.0)
Requires-Dist: poetry-dynamic-versioning (>=1.1.0,<2.0.0)
Project-URL: Repository, https://github.com/peerdom/peerdom-client-python/
